{"vab_echarts.md":"kyy7pTw_","vab_formtable.md":"0KMi4ga9","vab_print.md":"CQoYS4Pu","vab_filterbar.md":"Bnfhr3p5","vab_tableselect.md":"obhp7wm7","guide_server.md":"Djlkc0S5","vab_tool.md":"DTcdZaCr","guide_iconfont.md":"B2Z_mzf8","guide_newpage.md":"DlzLcfz8","guide_style.md":"YXOv4s5k","index.md":"Bv4ZVweM","guide_global.md":"CYjCZBuc","guide_codestyle.md":"DnF5HjB_","vab_index.md":"DPFvKGDp","vab_contextmenu.md":"DOtVoxRA","guide_404.md":"Ci4Bu6Dd","vab_ing.md":"BmWUj5P6","vab_table.md":"Bnz0pr4o","vab_cropper.md":"B2TzO2jX","vab_statistic.md":"C2Uz-mcw","vab_editor.md":"D4Xnismc","guide_router.md":"F5Vgh1tV","guide_splitmod.md":"B2YVUDKN","vab_upload.md":"CjmHnO9J","guide_build.md":"DnQrkWd9","guide_index.md":"DX4md8E2"}
